spladerunner/Config.py
spladerunner/Expander.py
spladerunner/__init__.py
SPLADERunner-0.1.6.dist-info/METADATA
SPLADERunner-0.1.6.dist-info/WHEEL
SPLADERunner-0.1.6.dist-info/top_level.txt
SPLADERunner-0.1.6.dist-info/RECORD
