Metadata-Version: 2.1
Name: SPLADERunner
Version: 0.1.6
Summary: Ultralight and Fast wrapper for the independent implementation of SPLADE++ models for your search & retrieval pipelines. Models and Library created by Prithivi Da, For PRs and Collaboration to checkout the readme.
Home-page: https://github.com/PrithivirajDamodaran/SPLADERunner
Author: Prithivi Da
Author-email: 
License: Apache 2.0
Classifier: Programming Language :: Python :: 3
Classifier: Operating System :: OS Independent
Requires-Python: >=3.6
Requires-Dist: tokenizers
Requires-Dist: onnxruntime
Requires-Dist: numpy
Requires-Dist: requests
Requires-Dist: tqdm
